poetry_lock_check/__init__.py
poetry_lock_check/__main__.py
poetry_lock_check-0.1.0.dist-info/WHEEL
poetry_lock_check-0.1.0.dist-info/METADATA
poetry_lock_check-0.1.0.dist-info/RECORD
