Metadata-Version: 2.1
Name: poetry-lock-check
Version: 0.1.0
Summary: Checks the lock on a poetry file
License: MIT
Author: Brian Graham
Author-email: brian@statagroup.com
Requires-Python: >=3.6,<4.0
Classifier: License :: OSI Approved :: MIT License
Classifier: Programming Language :: Python :: 3
Classifier: Programming Language :: Python :: 3.6
Classifier: Programming Language :: Python :: 3.7
Classifier: Programming Language :: Python :: 3.8
Classifier: Programming Language :: Python :: 3.9
Requires-Dist: cleo
Requires-Dist: poetry (>=1.1.0,<2.0.0)
